interview_ai/__init__.py
interview_ai/cli/setup.py
interview_ai/clients/__init__.py
interview_ai/clients/interview_client.py
interview_ai/core/__init__.py
interview_ai/core/cache.py
interview_ai/core/llms.py
interview_ai/core/operators.py
interview_ai/core/prompts.py
interview_ai/core/schemas.py
interview_ai/core/settings.py
interview_ai/core/storage.py
interview_ai/core/tools.py
interview_ai/core/utilities.py
interview_ai/servers/__init__.py
interview_ai/servers/interview_server.py
interview_ai-1.1.0.dist-info/licenses/LICENSE
interview_ai-1.1.0.dist-info/METADATA
interview_ai-1.1.0.dist-info/WHEEL
interview_ai-1.1.0.dist-info/entry_points.txt
interview_ai-1.1.0.dist-info/top_level.txt
interview_ai-1.1.0.dist-info/RECORD
