Metadata-Version: 2.4
Name: interview-ai
Version: 1.1.0
Summary: AI-powered interview automation with LangGraph. Conduct, evaluate, and report on technical interviews.
Author-email: Ankit Pal <ankitpal181@gmail.com>
Project-URL: Documentation, https://toonformatter.net/docs.html?package=interview-ai
Project-URL: Download, https://pypi.org/project/interview-ai/#files
Project-URL: Source, https://github.com/ankitpal181/interview-ai
Project-URL: Bug Tracker, https://github.com/ankitpal181/interview-ai/issues
Project-URL: Funding, https://github.com/sponsors/ankitpal181
Classifier: Programming Language :: Python :: 3.10
Classifier: Programming Language :: Python :: 3.11
Classifier: Programming Language :: Python :: 3.12
Classifier: Programming Language :: Python :: 3.13
Classifier: Topic :: Software Development
Classifier: License :: OSI Approved :: MIT License
Classifier: Operating System :: OS Independent
Classifier: Intended Audience :: Developers
Classifier: Intended Audience :: Education
Classifier: Development Status :: 4 - Beta
Requires-Python: >=3.10
License-File: LICENSE
Requires-Dist: ddgs>=9.6.1
Requires-Dist: langchain_community>=0.4.1
Requires-Dist: langchain_core>=1.2.4
Requires-Dist: langchain_google_genai>=4.1.2
Requires-Dist: langchain_openai>=1.1.6
Requires-Dist: langgraph>=1.0.5
Requires-Dist: langgraph-checkpoint-mongodb>=0.2.1
Requires-Dist: langgraph-checkpoint-postgres>=3.0.0
Requires-Dist: langgraph-checkpoint-sqlite>=2.0.11
Requires-Dist: langgraph-prebuilt>=1.0.2
Requires-Dist: langsmith>=0.5.0
Requires-Dist: pandas>=2.3.3
Requires-Dist: psycopg>=3.2.12
Requires-Dist: psycopg-binary>=3.2.12
Requires-Dist: pydantic>=2.12.5
Requires-Dist: pydantic-settings>=2.0.0
Requires-Dist: pymongo>=4.15.5
Requires-Dist: requests>=2.32.5
Requires-Dist: toon-parse>=2.4.3
Requires-Dist: torch>=2.9.1
Requires-Dist: transformers>=4.57.3
Requires-Dist: speechrecognition>=3.14.3
Requires-Dist: weasyprint>=67.0
Dynamic: license-file
